benchify/__init__.py
benchify/_base_client.py
benchify/_client.py
benchify/_compat.py
benchify/_constants.py
benchify/_exceptions.py
benchify/_files.py
benchify/_models.py
benchify/_qs.py
benchify/_resource.py
benchify/_response.py
benchify/_streaming.py
benchify/_types.py
benchify/_version.py
benchify/py.typed
benchify/_utils/__init__.py
benchify/_utils/_compat.py
benchify/_utils/_datetime_parse.py
benchify/_utils/_logs.py
benchify/_utils/_proxy.py
benchify/_utils/_reflection.py
benchify/_utils/_resources_proxy.py
benchify/_utils/_streams.py
benchify/_utils/_sync.py
benchify/_utils/_transform.py
benchify/_utils/_typing.py
benchify/_utils/_utils.py
benchify/lib/.keep
benchify/resources/__init__.py
benchify/resources/fix_parsing_and_diagnose.py
benchify/resources/fix_string_literals.py
benchify/resources/fixer.py
benchify/resources/stacks.py
benchify/resources/validate_template.py
benchify/resources/fix/__init__.py
benchify/resources/fix/fix.py
benchify/resources/fix/standard.py
benchify/types/__init__.py
benchify/types/fix_create_ai_fallback_params.py
benchify/types/fix_create_ai_fallback_response.py
benchify/types/fix_parsing_and_diagnose_detect_issues_params.py
benchify/types/fix_parsing_and_diagnose_detect_issues_response.py
benchify/types/fix_string_literal_create_params.py
benchify/types/fix_string_literal_create_response.py
benchify/types/fixer_run_params.py
benchify/types/fixer_run_response.py
benchify/types/stack_create_and_run_params.py
benchify/types/stack_create_and_run_response.py
benchify/types/stack_create_params.py
benchify/types/stack_create_response.py
benchify/types/stack_execute_command_params.py
benchify/types/stack_execute_command_response.py
benchify/types/stack_get_logs_params.py
benchify/types/stack_get_logs_response.py
benchify/types/stack_get_network_info_response.py
benchify/types/stack_read_file_params.py
benchify/types/stack_read_file_response.py
benchify/types/stack_reset_params.py
benchify/types/stack_reset_response.py
benchify-0.7.0.dist-info/METADATA
benchify-0.7.0.dist-info/WHEEL
benchify-0.7.0.dist-info/licenses/LICENSE
benchify-0.7.0.dist-info/RECORD
